haqc/__init__.py
haqc/algorithms/eval_qaoa.py
haqc/build_circuit.py
haqc/build_graph.py
haqc/classical/greedy_tsp.py
haqc/classical/maxcut.py
haqc/clustering.py
haqc/exp_utils.py
haqc/features/graph_features.py
haqc/features/tsp_features.py
haqc/generators/generator_utils.py
haqc/generators/graph_instance.py
haqc/generators/parameter.py
haqc/generators/random_instances.py
haqc/initialisation/initialisation.py
haqc/initialisation/parameter_fixing.py
haqc/nelder_mead.py
haqc/parallel/landscape_parallel.py
haqc/parallel/optimize_qaoa.py
haqc/parallel/optimize_qaoa_sv.py
haqc/plot/approximation_ratio.py
haqc/plot/draw_euclidean_graphs.py
haqc/plot/draw_networks.py
haqc/plot/feasibility_graph.py
haqc/plot/landscape.py
haqc/plot/utils.py
haqc/quantum_burden.py
haqc/rqaoa_main.py
haqc/run_initial_methods.py
haqc/run_nelder_mead.py
haqc/run_optimizers.py
haqc/run_optimizers_parallel.py
haqc/run_tsp.py
haqc/solutions/solutions.py
haqc/utils.py
haqc-1.0.3.dist-info/LICENSE
haqc-1.0.3.dist-info/METADATA
haqc-1.0.3.dist-info/WHEEL
haqc-1.0.3.dist-info/RECORD
