Metadata-Version: 2.1
Name: haqc
Version: 1.0.3
Summary: A Heuristic Algorithm Framework for Quantum Algorithms
Author: Vivek Katial
Author-email: vivekkatial@gmail.com
Requires-Python: >=3.8,<4.0
Classifier: Programming Language :: Python :: 3
Classifier: Programming Language :: Python :: 3.8
Classifier: Programming Language :: Python :: 3.9
Classifier: Programming Language :: Python :: 3.10
Classifier: Programming Language :: Python :: 3.11
Classifier: Programming Language :: Python :: 3.12
Requires-Dist: Jinja2 (==3.1.2)
Requires-Dist: Mako (==1.2.3)
Requires-Dist: MarkupSafe (==2.1.1)
Requires-Dist: PyYAML (==6.0.1)
Requires-Dist: SQLAlchemy (==1.4.42)
Requires-Dist: black (==22.10.0)
Requires-Dist: boto3 (==1.24.91)
Requires-Dist: botocore (==1.27.91)
Requires-Dist: build (>=1.0.3,<2.0.0)
Requires-Dist: certifi (==2022.9.24)
Requires-Dist: cffi (==1.15.1)
Requires-Dist: charset-normalizer (==2.1.1)
Requires-Dist: click (==8.1.3)
Requires-Dist: cvxpy (>=1.4.2,<2.0.0)
Requires-Dist: iniconfig (==1.1.1)
Requires-Dist: ipykernel (==6.16.0)
Requires-Dist: ipython (==8.4.0)
Requires-Dist: ipywidgets (==8.0.2)
Requires-Dist: itsdangerous (==2.1.2)
Requires-Dist: jedi (==0.18.1)
Requires-Dist: jmespath (==1.0.1)
Requires-Dist: kiwisolver (==1.4.4)
Requires-Dist: matplotlib (==3.6.1)
Requires-Dist: matplotlib-inline (==0.1.6)
Requires-Dist: mlflow (==2.9.2)
Requires-Dist: networkx (==2.8.7)
Requires-Dist: numpy (==1.23.4)
Requires-Dist: oauthlib (==3.2.1)
Requires-Dist: packaging (==21.3)
Requires-Dist: pandas (==1.5.0)
Requires-Dist: parso (==0.8.3)
Requires-Dist: plotly (>=5.18.0,<6.0.0)
Requires-Dist: pylatexenc (>=2.10,<3.0)
Requires-Dist: pynauty (>=2.8.6,<3.0.0)
Requires-Dist: pytest (==7.1.3)
Requires-Dist: python-dateutil (==2.8.2)
Requires-Dist: python-louvain (==0.16)
Requires-Dist: pytz (==2022.4)
Requires-Dist: pyzmq (==24.0.1)
Requires-Dist: qiskit (==0.39.0)
Requires-Dist: qiskit-aer (==0.11.0)
Requires-Dist: qiskit-ibmq-provider (==0.19.2)
Requires-Dist: qiskit-optimization (==0.4.0)
Requires-Dist: qiskit-terra (==0.22.0)
Requires-Dist: querystring-parser (==1.2.4)
Requires-Dist: requests (==2.28.1)
Requires-Dist: requests_ntlm (==1.1.0)
Requires-Dist: retworkx (==0.12.0)
Requires-Dist: rustworkx (==0.12.0)
Requires-Dist: s3transfer (==0.6.0)
Requires-Dist: scipy (>=1.5.0,<1.11.0)
Requires-Dist: seaborn (==0.12.0)
Requires-Dist: six (==1.16.0)
Requires-Dist: smmap (==5.0.0)
Requires-Dist: sympy (==1.11.1)
Requires-Dist: tqdm (>=4.66.1,<5.0.0)
